{
  "meta": {
    "schemaVersion": 2,
    "parent": "af"
  },
  "zones": [
    {
      "id": "af-kbl",
      "name": "Kabul Province",
      "level": "state",
      "parent": "af",
      "hasChildren": false,
      "geo": {
        "lat": 34.53,
        "lng": 69.17,
        "flag": "🏴",
        "region": "Asia"
      },
      "accessTier": "fortress",
      "biome": "Urban Outpost",
      "lore": "Kabul Province is a curated regional zone in Afghanistan.",
      "stats": {
        "wealth": {
          "monthly_usd": 315,
          "annual_usd": 3780
        },
        "language": {
          "primary": "Dari/Pashto",
          "others": [],
          "test": "none",
          "level": "none"
        },
        "skills": {
          "preferred": [
            "Humanitarian",
            "Public Health",
            "Logistics",
            "Education"
          ],
          "degreeRequired": false
        },
        "health": "proof_required",
        "age": {
          "min": null,
          "max": null
        }
      },
      "quests": [
        {
          "id": "local_path",
          "type": "hard",
          "label": "National pathway + local settlement",
          "detail": "Local compliance and labor demand shape onboarding speed.",
          "options": []
        }
      ],
      "difficulty": {
        "overall": 98,
        "cost": 10,
        "safety": 4,
        "quality": 16,
        "language": 54,
        "security": 5
      },
      "population": 6000000,
      "currency": "AFN"
    },
    {
      "id": "af-hrt",
      "name": "Herat Province",
      "level": "state",
      "parent": "af",
      "hasChildren": false,
      "geo": {
        "lat": 34.35,
        "lng": 62.2,
        "flag": "🏴",
        "region": "Asia"
      },
      "accessTier": "fortress",
      "biome": "Border Territory",
      "lore": "Herat Province is a curated regional zone in Afghanistan.",
      "stats": {
        "wealth": {
          "monthly_usd": 315,
          "annual_usd": 3780
        },
        "language": {
          "primary": "Dari/Pashto",
          "others": [],
          "test": "none",
          "level": "none"
        },
        "skills": {
          "preferred": [
            "Humanitarian",
            "Public Health",
            "Logistics",
            "Education"
          ],
          "degreeRequired": false
        },
        "health": "proof_required",
        "age": {
          "min": null,
          "max": null
        }
      },
      "quests": [
        {
          "id": "local_path",
          "type": "hard",
          "label": "National pathway + local settlement",
          "detail": "Local compliance and labor demand shape onboarding speed.",
          "options": []
        }
      ],
      "difficulty": {
        "overall": 95,
        "cost": 6,
        "safety": 6,
        "quality": 12,
        "language": 58,
        "security": 8
      },
      "population": 2200000,
      "currency": "AFN"
    }
  ]
}
